{
  "name": "graphql",
  "rules": {
    "source_file": {
      "type": "SYMBOL",
      "name": "document"
    },
    "document": {
      "type": "REPEAT1",
      "content": {
        "type": "SYMBOL",
        "name": "definition"
      }
    },
    "definition": {
      "type": "CHOICE",
      "members": [
        {
          "type": "SYMBOL",
          "name": "executable_definition"
        },
        {
          "type": "SYMBOL",
          "name": "type_system_definition"
        },
        {
          "type": "SYMBOL",
          "name": "type_system_extension"
        }
      ]
    },
    "executable_definition": {
      "type": "CHOICE",
      "members": [
        {
          "type": "SYMBOL",
          "name": "operation_definition"
        },
        {
          "type": "SYMBOL",
          "name": "fragment_definition"
        }
      ]
    },
    "type_system_definition": {
      "type": "CHOICE",
      "members": [
        {
          "type": "SYMBOL",
          "name": "schema_definition"
        },
        {
          "type": "SYMBOL",
          "name": "type_definition"
        },
        {
          "type": "SYMBOL",
          "name": "directive_definition"
        }
      ]
    },
    "type_system_extension": {
      "type": "CHOICE",
      "members": [
        {
          "type": "SYMBOL",
          "name": "schema_extension"
        },
        {
          "type": "SYMBOL",
          "name": "type_extension"
        }
      ]
    },
    "schema_definition": {
      "type": "SEQ",
      "members": [
        {
          "type": "CHOICE",
          "members": [
            {
              "type": "SYMBOL",
              "name": "description"
            },
            {
              "type": "BLANK"
            }
          ]
        },
        {
          "type": "STRING",
          "value": "schema"
        },
        {
          "type": "CHOICE",
          "members": [
            {
              "type": "SYMBOL",
              "name": "directives"
            },
            {
              "type": "BLANK"
            }
          ]
        },
        {
          "type": "STRING",
          "value": "{"
        },
        {
          "type": "REPEAT1",
          "content": {
            "type": "SYMBOL",
            "name": "root_operation_type_definition"
          }
        },
        {
          "type": "STRING",
          "value": "}"
        }
      ]
    },
    "schema_extension": {
      "type": "SEQ",
      "members": [
        {
          "type": "STRING",
          "value": "extend"
        },
        {
          "type": "STRING",
          "value": "schema"
        },
        {
          "type": "CHOICE",
          "members": [
            {
              "type": "SYMBOL",
              "name": "directives"
            },
            {
              "type": "BLANK"
            }
          ]
        },
        {
          "type": "STRING",
          "value": "{"
        },
        {
          "type": "SYMBOL",
          "name": "root_operation_type_definition"
        },
        {
          "type": "STRING",
          "value": "}"
        }
      ]
    },
    "type_extension": {
      "type": "CHOICE",
      "members": [
        {
          "type": "SYMBOL",
          "name": "scalar_type_extension"
        },
        {
          "type": "SYMBOL",
          "name": "object_type_extension"
        },
        {
          "type": "SYMBOL",
          "name": "interface_type_extension"
        },
        {
          "type": "SYMBOL",
          "name": "union_type_extension"
        },
        {
          "type": "SYMBOL",
          "name": "enum_type_extension"
        },
        {
          "type": "SYMBOL",
          "name": "input_object_type_extension"
        }
      ]
    },
    "scalar_type_extension": {
      "type": "SEQ",
      "members": [
        {
          "type": "STRING",
          "value": "extend"
        },
        {
          "type": "STRING",
          "value": "scalar"
        },
        {
          "type": "SYMBOL",
          "name": "name"
        },
        {
          "type": "SYMBOL",
          "name": "directives"
        }
      ]
    },
    "object_type_extension": {
      "type": "PREC_RIGHT",
      "value": 0,
      "content": {
        "type": "CHOICE",
        "members": [
          {
            "type": "SEQ",
            "members": [
              {
                "type": "STRING",
                "value": "extend"
              },
              {
                "type": "STRING",
                "value": "type"
              },
              {
                "type": "SYMBOL",
                "name": "name"
              },
              {
                "type": "CHOICE",
                "members": [
                  {
                    "type": "SYMBOL",
                    "name": "implements_interfaces"
                  },
                  {
                    "type": "BLANK"
                  }
                ]
              },
              {
                "type": "CHOICE",
                "members": [
                  {
                    "type": "SYMBOL",
                    "name": "directives"
                  },
                  {
                    "type": "BLANK"
                  }
                ]
              },
              {
                "type": "SYMBOL",
                "name": "fields_definition"
              }
            ]
          },
          {
            "type": "SEQ",
            "members": [
              {
                "type": "STRING",
                "value": "extend"
              },
              {
                "type": "STRING",
                "value": "type"
              },
              {
                "type": "SYMBOL",
                "name": "name"
              },
              {
                "type": "CHOICE",
                "members": [
                  {
                    "type": "SYMBOL",
                    "name": "implements_interfaces"
                  },
                  {
                    "type": "BLANK"
                  }
                ]
              },
              {
                "type": "CHOICE",
                "members": [
                  {
                    "type": "SYMBOL",
                    "name": "directives"
                  },
                  {
                    "type": "BLANK"
                  }
                ]
              }
            ]
          }
        ]
      }
    },
    "interface_type_extension": {
      "type": "PREC_RIGHT",
      "value": 0,
      "content": {
        "type": "CHOICE",
        "members": [
          {
            "type": "SEQ",
            "members": [
              {
                "type": "STRING",
                "value": "extend"
              },
              {
                "type": "STRING",
                "value": "interface"
              },
              {
                "type": "SYMBOL",
                "name": "name"
              },
              {
                "type": "CHOICE",
                "members": [
                  {
                    "type": "SYMBOL",
                    "name": "implements_interfaces"
                  },
                  {
                    "type": "BLANK"
                  }
                ]
              },
              {
                "type": "CHOICE",
                "members": [
                  {
                    "type": "SYMBOL",
                    "name": "directives"
                  },
                  {
                    "type": "BLANK"
                  }
                ]
              },
              {
                "type": "SYMBOL",
                "name": "fields_definition"
              }
            ]
          },
          {
            "type": "SEQ",
            "members": [
              {
                "type": "STRING",
                "value": "extend"
              },
              {
                "type": "STRING",
                "value": "interface"
              },
              {
                "type": "SYMBOL",
                "name": "name"
              },
              {
                "type": "CHOICE",
                "members": [
                  {
                    "type": "SYMBOL",
                    "name": "implements_interfaces"
                  },
                  {
                    "type": "BLANK"
                  }
                ]
              },
              {
                "type": "CHOICE",
                "members": [
                  {
                    "type": "SYMBOL",
                    "name": "directives"
                  },
                  {
                    "type": "BLANK"
                  }
                ]
              }
            ]
          }
        ]
      }
    },
    "union_type_extension": {
      "type": "PREC_RIGHT",
      "value": 0,
      "content": {
        "type": "CHOICE",
        "members": [
          {
            "type": "SEQ",
            "members": [
              {
                "type": "STRING",
                "value": "extend"
              },
              {
                "type": "STRING",
                "value": "union"
              },
              {
                "type": "SYMBOL",
                "name": "name"
              },
              {
                "type": "CHOICE",
                "members": [
                  {
                    "type": "SYMBOL",
                    "name": "directives"
                  },
                  {
                    "type": "BLANK"
                  }
                ]
              },
              {
                "type": "SYMBOL",
                "name": "union_member_types"
              }
            ]
          },
          {
            "type": "SEQ",
            "members": [
              {
                "type": "STRING",
                "value": "extend"
              },
              {
                "type": "STRING",
                "value": "union"
              },
              {
                "type": "SYMBOL",
                "name": "name"
              },
              {
                "type": "CHOICE",
                "members": [
                  {
                    "type": "SYMBOL",
                    "name": "directives"
                  },
                  {
                    "type": "BLANK"
                  }
                ]
              }
            ]
          }
        ]
      }
    },
    "enum_type_extension": {
      "type": "PREC_RIGHT",
      "value": 0,
      "content": {
        "type": "CHOICE",
        "members": [
          {
            "type": "SEQ",
            "members": [
              {
                "type": "STRING",
                "value": "extend"
              },
              {
                "type": "STRING",
                "value": "enum"
              },
              {
                "type": "SYMBOL",
                "name": "name"
              },
              {
                "type": "CHOICE",
                "members": [
                  {
                    "type": "SYMBOL",
                    "name": "directives"
                  },
                  {
                    "type": "BLANK"
                  }
                ]
              },
              {
                "type": "SYMBOL",
                "name": "enum_values_definition"
              }
            ]
          },
          {
            "type": "SEQ",
            "members": [
              {
                "type": "STRING",
                "value": "extend"
              },
              {
                "type": "STRING",
                "value": "enum"
              },
              {
                "type": "SYMBOL",
                "name": "name"
              },
              {
                "type": "CHOICE",
                "members": [
                  {
                    "type": "SYMBOL",
                    "name": "directives"
                  },
                  {
                    "type": "BLANK"
                  }
                ]
              }
            ]
          }
        ]
      }
    },
    "input_object_type_extension": {
      "type": "PREC_RIGHT",
      "value": 0,
      "content": {
        "type": "CHOICE",
        "members": [
          {
            "type": "SEQ",
            "members": [
              {
                "type": "STRING",
                "value": "extend"
              },
              {
                "type": "STRING",
                "value": "input"
              },
              {
                "type": "SYMBOL",
                "name": "name"
              },
              {
                "type": "CHOICE",
                "members": [
                  {
                    "type": "SYMBOL",
                    "name": "directives"
                  },
                  {
                    "type": "BLANK"
                  }
                ]
              },
              {
                "type": "REPEAT1",
                "content": {
                  "type": "SYMBOL",
                  "name": "input_fields_definition"
                }
              }
            ]
          },
          {
            "type": "SEQ",
            "members": [
              {
                "type": "STRING",
                "value": "extend"
              },
              {
                "type": "STRING",
                "value": "input"
              },
              {
                "type": "SYMBOL",
                "name": "name"
              },
              {
                "type": "CHOICE",
                "members": [
                  {
                    "type": "SYMBOL",
                    "name": "directives"
                  },
                  {
                    "type": "BLANK"
                  }
                ]
              }
            ]
          }
        ]
      }
    },
    "input_fields_definition": {
      "type": "SEQ",
      "members": [
        {
          "type": "STRING",
          "value": "{"
        },
        {
          "type": "REPEAT1",
          "content": {
            "type": "SYMBOL",
            "name": "input_value_definition"
          }
        },
        {
          "type": "STRING",
          "value": "}"
        }
      ]
    },
    "enum_values_definition": {
      "type": "SEQ",
      "members": [
        {
          "type": "STRING",
          "value": "{"
        },
        {
          "type": "REPEAT1",
          "content": {
            "type": "SYMBOL",
            "name": "enum_value_definition"
          }
        },
        {
          "type": "STRING",
          "value": "}"
        }
      ]
    },
    "enum_value_definition": {
      "type": "SEQ",
      "members": [
        {
          "type": "CHOICE",
          "members": [
            {
              "type": "SYMBOL",
              "name": "description"
            },
            {
              "type": "BLANK"
            }
          ]
        },
        {
          "type": "SYMBOL",
          "name": "enum_value"
        },
        {
          "type": "CHOICE",
          "members": [
            {
              "type": "SYMBOL",
              "name": "directives"
            },
            {
              "type": "BLANK"
            }
          ]
        }
      ]
    },
    "implements_interfaces": {
      "type": "CHOICE",
      "members": [
        {
          "type": "SEQ",
          "members": [
            {
              "type": "SYMBOL",
              "name": "implements_interfaces"
            },
            {
              "type": "STRING",
              "value": "&"
            },
            {
              "type": "SYMBOL",
              "name": "named_type"
            }
          ]
        },
        {
          "type": "SEQ",
          "members": [
            {
              "type": "STRING",
              "value": "implements"
            },
            {
              "type": "CHOICE",
              "members": [
                {
                  "type": "STRING",
                  "value": "&"
                },
                {
                  "type": "BLANK"
                }
              ]
            },
            {
              "type": "SYMBOL",
              "name": "named_type"
            }
          ]
        }
      ]
    },
    "fields_definition": {
      "type": "SEQ",
      "members": [
        {
          "type": "STRING",
          "value": "{"
        },
        {
          "type": "REPEAT1",
          "content": {
            "type": "SYMBOL",
            "name": "field_definition"
          }
        },
        {
          "type": "STRING",
          "value": "}"
        }
      ]
    },
    "field_definition": {
      "type": "SEQ",
      "members": [
        {
          "type": "CHOICE",
          "members": [
            {
              "type": "SYMBOL",
              "name": "description"
            },
            {
              "type": "BLANK"
            }
          ]
        },
        {
          "type": "SYMBOL",
          "name": "name"
        },
        {
          "type": "CHOICE",
          "members": [
            {
              "type": "SYMBOL",
              "name": "arguments_definition"
            },
            {
              "type": "BLANK"
            }
          ]
        },
        {
          "type": "STRING",
          "value": ":"
        },
        {
          "type": "SYMBOL",
          "name": "type"
        },
        {
          "type": "CHOICE",
          "members": [
            {
              "type": "SYMBOL",
              "name": "directives"
            },
            {
              "type": "BLANK"
            }
          ]
        }
      ]
    },
    "arguments_definition": {
      "type": "SEQ",
      "members": [
        {
          "type": "STRING",
          "value": "("
        },
        {
          "type": "REPEAT1",
          "content": {
            "type": "SYMBOL",
            "name": "input_value_definition"
          }
        },
        {
          "type": "STRING",
          "value": ")"
        }
      ]
    },
    "input_value_definition": {
      "type": "SEQ",
      "members": [
        {
          "type": "CHOICE",
          "members": [
            {
              "type": "SYMBOL",
              "name": "description"
            },
            {
              "type": "BLANK"
            }
          ]
        },
        {
          "type": "SYMBOL",
          "name": "name"
        },
        {
          "type": "STRING",
          "value": ":"
        },
        {
          "type": "SYMBOL",
          "name": "type"
        },
        {
          "type": "CHOICE",
          "members": [
            {
              "type": "SYMBOL",
              "name": "default_value"
            },
            {
              "type": "BLANK"
            }
          ]
        },
        {
          "type": "CHOICE",
          "members": [
            {
              "type": "SYMBOL",
              "name": "directives"
            },
            {
              "type": "BLANK"
            }
          ]
        }
      ]
    },
    "default_value": {
      "type": "SEQ",
      "members": [
        {
          "type": "STRING",
          "value": "="
        },
        {
          "type": "SYMBOL",
          "name": "value"
        }
      ]
    },
    "union_member_types": {
      "type": "CHOICE",
      "members": [
        {
          "type": "SEQ",
          "members": [
            {
              "type": "SYMBOL",
              "name": "union_member_types"
            },
            {
              "type": "STRING",
              "value": "|"
            },
            {
              "type": "SYMBOL",
              "name": "named_type"
            }
          ]
        },
        {
          "type": "SEQ",
          "members": [
            {
              "type": "STRING",
              "value": "="
            },
            {
              "type": "CHOICE",
              "members": [
                {
                  "type": "STRING",
                  "value": "|"
                },
                {
                  "type": "BLANK"
                }
              ]
            },
            {
              "type": "SYMBOL",
              "name": "named_type"
            }
          ]
        }
      ]
    },
    "root_operation_type_definition": {
      "type": "SEQ",
      "members": [
        {
          "type": "SYMBOL",
          "name": "operation_type"
        },
        {
          "type": "STRING",
          "value": ":"
        },
        {
          "type": "SYMBOL",
          "name": "named_type"
        }
      ]
    },
    "operation_definition": {
      "type": "CHOICE",
      "members": [
        {
          "type": "SYMBOL",
          "name": "selection_set"
        },
        {
          "type": "SEQ",
          "members": [
            {
              "type": "SYMBOL",
              "name": "operation_type"
            },
            {
              "type": "CHOICE",
              "members": [
                {
                  "type": "SYMBOL",
                  "name": "name"
                },
                {
                  "type": "BLANK"
                }
              ]
            },
            {
              "type": "CHOICE",
              "members": [
                {
                  "type": "SYMBOL",
                  "name": "variable_definitions"
                },
                {
                  "type": "BLANK"
                }
              ]
            },
            {
              "type": "CHOICE",
              "members": [
                {
                  "type": "SYMBOL",
                  "name": "directives"
                },
                {
                  "type": "BLANK"
                }
              ]
            },
            {
              "type": "SYMBOL",
              "name": "selection_set"
            }
          ]
        }
      ]
    },
    "operation_type": {
      "type": "CHOICE",
      "members": [
        {
          "type": "STRING",
          "value": "query"
        },
        {
          "type": "STRING",
          "value": "mutation"
        },
        {
          "type": "STRING",
          "value": "subscription"
        }
      ]
    },
    "type_definition": {
      "type": "CHOICE",
      "members": [
        {
          "type": "SYMBOL",
          "name": "scalar_type_definition"
        },
        {
          "type": "SYMBOL",
          "name": "object_type_definition"
        },
        {
          "type": "SYMBOL",
          "name": "interface_type_definition"
        },
        {
          "type": "SYMBOL",
          "name": "union_type_definition"
        },
        {
          "type": "SYMBOL",
          "name": "enum_type_definition"
        },
        {
          "type": "SYMBOL",
          "name": "input_object_type_definition"
        }
      ]
    },
    "scalar_type_definition": {
      "type": "PREC_RIGHT",
      "value": 0,
      "content": {
        "type": "SEQ",
        "members": [
          {
            "type": "CHOICE",
            "members": [
              {
                "type": "SYMBOL",
                "name": "description"
              },
              {
                "type": "BLANK"
              }
            ]
          },
          {
            "type": "STRING",
            "value": "scalar"
          },
          {
            "type": "SYMBOL",
            "name": "name"
          },
          {
            "type": "CHOICE",
            "members": [
              {
                "type": "SYMBOL",
                "name": "directives"
              },
              {
                "type": "BLANK"
              }
            ]
          }
        ]
      }
    },
    "object_type_definition": {
      "type": "PREC_RIGHT",
      "value": 0,
      "content": {
        "type": "SEQ",
        "members": [
          {
            "type": "CHOICE",
            "members": [
              {
                "type": "SYMBOL",
                "name": "description"
              },
              {
                "type": "BLANK"
              }
            ]
          },
          {
            "type": "STRING",
            "value": "type"
          },
          {
            "type": "SYMBOL",
            "name": "name"
          },
          {
            "type": "CHOICE",
            "members": [
              {
                "type": "SYMBOL",
                "name": "implements_interfaces"
              },
              {
                "type": "BLANK"
              }
            ]
          },
          {
            "type": "CHOICE",
            "members": [
              {
                "type": "SYMBOL",
                "name": "directives"
              },
              {
                "type": "BLANK"
              }
            ]
          },
          {
            "type": "CHOICE",
            "members": [
              {
                "type": "SYMBOL",
                "name": "fields_definition"
              },
              {
                "type": "BLANK"
              }
            ]
          }
        ]
      }
    },
    "interface_type_definition": {
      "type": "PREC_RIGHT",
      "value": 0,
      "content": {
        "type": "SEQ",
        "members": [
          {
            "type": "CHOICE",
            "members": [
              {
                "type": "SYMBOL",
                "name": "description"
              },
              {
                "type": "BLANK"
              }
            ]
          },
          {
            "type": "STRING",
            "value": "interface"
          },
          {
            "type": "SYMBOL",
            "name": "name"
          },
          {
            "type": "CHOICE",
            "members": [
              {
                "type": "SYMBOL",
                "name": "implements_interfaces"
              },
              {
                "type": "BLANK"
              }
            ]
          },
          {
            "type": "CHOICE",
            "members": [
              {
                "type": "SYMBOL",
                "name": "directives"
              },
              {
                "type": "BLANK"
              }
            ]
          },
          {
            "type": "CHOICE",
            "members": [
              {
                "type": "SYMBOL",
                "name": "fields_definition"
              },
              {
                "type": "BLANK"
              }
            ]
          }
        ]
      }
    },
    "union_type_definition": {
      "type": "PREC_RIGHT",
      "value": 0,
      "content": {
        "type": "SEQ",
        "members": [
          {
            "type": "CHOICE",
            "members": [
              {
                "type": "SYMBOL",
                "name": "description"
              },
              {
                "type": "BLANK"
              }
            ]
          },
          {
            "type": "STRING",
            "value": "union"
          },
          {
            "type": "SYMBOL",
            "name": "name"
          },
          {
            "type": "CHOICE",
            "members": [
              {
                "type": "SYMBOL",
                "name": "directives"
              },
              {
                "type": "BLANK"
              }
            ]
          },
          {
            "type": "CHOICE",
            "members": [
              {
                "type": "SYMBOL",
                "name": "union_member_types"
              },
              {
                "type": "BLANK"
              }
            ]
          }
        ]
      }
    },
    "enum_type_definition": {
      "type": "PREC_RIGHT",
      "value": 0,
      "content": {
        "type": "SEQ",
        "members": [
          {
            "type": "CHOICE",
            "members": [
              {
                "type": "SYMBOL",
                "name": "description"
              },
              {
                "type": "BLANK"
              }
            ]
          },
          {
            "type": "STRING",
            "value": "enum"
          },
          {
            "type": "SYMBOL",
            "name": "name"
          },
          {
            "type": "CHOICE",
            "members": [
              {
                "type": "SYMBOL",
                "name": "directives"
              },
              {
                "type": "BLANK"
              }
            ]
          },
          {
            "type": "CHOICE",
            "members": [
              {
                "type": "SYMBOL",
                "name": "enum_values_definition"
              },
              {
                "type": "BLANK"
              }
            ]
          }
        ]
      }
    },
    "input_object_type_definition": {
      "type": "PREC_RIGHT",
      "value": 0,
      "content": {
        "type": "SEQ",
        "members": [
          {
            "type": "CHOICE",
            "members": [
              {
                "type": "SYMBOL",
                "name": "description"
              },
              {
                "type": "BLANK"
              }
            ]
          },
          {
            "type": "STRING",
            "value": "input"
          },
          {
            "type": "SYMBOL",
            "name": "name"
          },
          {
            "type": "CHOICE",
            "members": [
              {
                "type": "SYMBOL",
                "name": "directives"
              },
              {
                "type": "BLANK"
              }
            ]
          },
          {
            "type": "CHOICE",
            "members": [
              {
                "type": "SYMBOL",
                "name": "input_fields_definition"
              },
              {
                "type": "BLANK"
              }
            ]
          }
        ]
      }
    },
    "variable_definitions": {
      "type": "SEQ",
      "members": [
        {
          "type": "STRING",
          "value": "("
        },
        {
          "type": "REPEAT1",
          "content": {
            "type": "SYMBOL",
            "name": "variable_definition"
          }
        },
        {
          "type": "STRING",
          "value": ")"
        }
      ]
    },
    "variable_definition": {
      "type": "SEQ",
      "members": [
        {
          "type": "SYMBOL",
          "name": "variable"
        },
        {
          "type": "STRING",
          "value": ":"
        },
        {
          "type": "SYMBOL",
          "name": "type"
        },
        {
          "type": "CHOICE",
          "members": [
            {
              "type": "SYMBOL",
              "name": "default_value"
            },
            {
              "type": "BLANK"
            }
          ]
        },
        {
          "type": "CHOICE",
          "members": [
            {
              "type": "SYMBOL",
              "name": "directives"
            },
            {
              "type": "BLANK"
            }
          ]
        },
        {
          "type": "CHOICE",
          "members": [
            {
              "type": "SYMBOL",
              "name": "comma"
            },
            {
              "type": "BLANK"
            }
          ]
        }
      ]
    },
    "selection_set": {
      "type": "SEQ",
      "members": [
        {
          "type": "STRING",
          "value": "{"
        },
        {
          "type": "REPEAT1",
          "content": {
            "type": "SYMBOL",
            "name": "selection"
          }
        },
        {
          "type": "STRING",
          "value": "}"
        }
      ]
    },
    "selection": {
      "type": "CHOICE",
      "members": [
        {
          "type": "SYMBOL",
          "name": "field"
        },
        {
          "type": "SYMBOL",
          "name": "inline_fragment"
        },
        {
          "type": "SYMBOL",
          "name": "fragment_spread"
        }
      ]
    },
    "field": {
      "type": "SEQ",
      "members": [
        {
          "type": "CHOICE",
          "members": [
            {
              "type": "SYMBOL",
              "name": "alias"
            },
            {
              "type": "BLANK"
            }
          ]
        },
        {
          "type": "SYMBOL",
          "name": "name"
        },
        {
          "type": "CHOICE",
          "members": [
            {
              "type": "SYMBOL",
              "name": "arguments"
            },
            {
              "type": "BLANK"
            }
          ]
        },
        {
          "type": "CHOICE",
          "members": [
            {
              "type": "SYMBOL",
              "name": "directive"
            },
            {
              "type": "BLANK"
            }
          ]
        },
        {
          "type": "CHOICE",
          "members": [
            {
              "type": "SYMBOL",
              "name": "selection_set"
            },
            {
              "type": "BLANK"
            }
          ]
        }
      ]
    },
    "alias": {
      "type": "SEQ",
      "members": [
        {
          "type": "SYMBOL",
          "name": "name"
        },
        {
          "type": "STRING",
          "value": ":"
        }
      ]
    },
    "arguments": {
      "type": "SEQ",
      "members": [
        {
          "type": "STRING",
          "value": "("
        },
        {
          "type": "REPEAT1",
          "content": {
            "type": "SYMBOL",
            "name": "argument"
          }
        },
        {
          "type": "STRING",
          "value": ")"
        }
      ]
    },
    "argument": {
      "type": "SEQ",
      "members": [
        {
          "type": "SYMBOL",
          "name": "name"
        },
        {
          "type": "STRING",
          "value": ":"
        },
        {
          "type": "SYMBOL",
          "name": "value"
        }
      ]
    },
    "value": {
      "type": "CHOICE",
      "members": [
        {
          "type": "SYMBOL",
          "name": "variable"
        },
        {
          "type": "SYMBOL",
          "name": "string_value"
        },
        {
          "type": "SYMBOL",
          "name": "int_value"
        },
        {
          "type": "SYMBOL",
          "name": "float_value"
        },
        {
          "type": "SYMBOL",
          "name": "boolean_value"
        },
        {
          "type": "SYMBOL",
          "name": "null_value"
        },
        {
          "type": "SYMBOL",
          "name": "enum_value"
        },
        {
          "type": "SYMBOL",
          "name": "list_value"
        },
        {
          "type": "SYMBOL",
          "name": "object_value"
        }
      ]
    },
    "variable": {
      "type": "SEQ",
      "members": [
        {
          "type": "STRING",
          "value": "$"
        },
        {
          "type": "SYMBOL",
          "name": "name"
        }
      ]
    },
    "string_value": {
      "type": "CHOICE",
      "members": [
        {
          "type": "SEQ",
          "members": [
            {
              "type": "STRING",
              "value": "\"\"\""
            },
            {
              "type": "PATTERN",
              "value": "([^\"]|\\n|\"\"?[^\"])*"
            },
            {
              "type": "STRING",
              "value": "\"\"\""
            }
          ]
        },
        {
          "type": "SEQ",
          "members": [
            {
              "type": "STRING",
              "value": "\""
            },
            {
              "type": "PATTERN",
              "value": "[^\"\\\\\\n]*"
            },
            {
              "type": "STRING",
              "value": "\""
            }
          ]
        }
      ]
    },
    "int_value": {
      "type": "PATTERN",
      "value": "-?(0|[1-9][0-9]*)"
    },
    "float_value": {
      "type": "TOKEN",
      "content": {
        "type": "SEQ",
        "members": [
          {
            "type": "PATTERN",
            "value": "-?(0|[1-9][0-9]*)"
          },
          {
            "type": "CHOICE",
            "members": [
              {
                "type": "PATTERN",
                "value": "\\.[0-9]+"
              },
              {
                "type": "PATTERN",
                "value": "(e|E)(\\+|-)?[0-9]+"
              },
              {
                "type": "SEQ",
                "members": [
                  {
                    "type": "PATTERN",
                    "value": "\\.[0-9]+"
                  },
                  {
                    "type": "PATTERN",
                    "value": "(e|E)(\\+|-)?[0-9]+"
                  }
                ]
              }
            ]
          }
        ]
      }
    },
    "boolean_value": {
      "type": "CHOICE",
      "members": [
        {
          "type": "STRING",
          "value": "true"
        },
        {
          "type": "STRING",
          "value": "false"
        }
      ]
    },
    "null_value": {
      "type": "STRING",
      "value": "null"
    },
    "enum_value": {
      "type": "SYMBOL",
      "name": "name"
    },
    "list_value": {
      "type": "SEQ",
      "members": [
        {
          "type": "STRING",
          "value": "["
        },
        {
          "type": "REPEAT",
          "content": {
            "type": "SYMBOL",
            "name": "value"
          }
        },
        {
          "type": "STRING",
          "value": "]"
        }
      ]
    },
    "object_value": {
      "type": "SEQ",
      "members": [
        {
          "type": "STRING",
          "value": "{"
        },
        {
          "type": "REPEAT",
          "content": {
            "type": "SYMBOL",
            "name": "object_field"
          }
        },
        {
          "type": "STRING",
          "value": "}"
        }
      ]
    },
    "object_field": {
      "type": "SEQ",
      "members": [
        {
          "type": "SYMBOL",
          "name": "name"
        },
        {
          "type": "STRING",
          "value": ":"
        },
        {
          "type": "SYMBOL",
          "name": "value"
        },
        {
          "type": "CHOICE",
          "members": [
            {
              "type": "SYMBOL",
              "name": "comma"
            },
            {
              "type": "BLANK"
            }
          ]
        }
      ]
    },
    "fragment_spread": {
      "type": "SEQ",
      "members": [
        {
          "type": "STRING",
          "value": "..."
        },
        {
          "type": "SYMBOL",
          "name": "fragment_name"
        },
        {
          "type": "CHOICE",
          "members": [
            {
              "type": "SYMBOL",
              "name": "directives"
            },
            {
              "type": "BLANK"
            }
          ]
        }
      ]
    },
    "fragment_definition": {
      "type": "SEQ",
      "members": [
        {
          "type": "STRING",
          "value": "fragment"
        },
        {
          "type": "SYMBOL",
          "name": "fragment_name"
        },
        {
          "type": "SYMBOL",
          "name": "type_condition"
        },
        {
          "type": "CHOICE",
          "members": [
            {
              "type": "SYMBOL",
              "name": "directives"
            },
            {
              "type": "BLANK"
            }
          ]
        },
        {
          "type": "SYMBOL",
          "name": "selection_set"
        }
      ]
    },
    "fragment_name": {
      "type": "SYMBOL",
      "name": "name"
    },
    "inline_fragment": {
      "type": "SEQ",
      "members": [
        {
          "type": "STRING",
          "value": "..."
        },
        {
          "type": "CHOICE",
          "members": [
            {
              "type": "SYMBOL",
              "name": "type_condition"
            },
            {
              "type": "BLANK"
            }
          ]
        },
        {
          "type": "CHOICE",
          "members": [
            {
              "type": "SYMBOL",
              "name": "directives"
            },
            {
              "type": "BLANK"
            }
          ]
        },
        {
          "type": "SYMBOL",
          "name": "selection_set"
        }
      ]
    },
    "type_condition": {
      "type": "SEQ",
      "members": [
        {
          "type": "STRING",
          "value": "on"
        },
        {
          "type": "SYMBOL",
          "name": "named_type"
        }
      ]
    },
    "directives": {
      "type": "REPEAT1",
      "content": {
        "type": "SYMBOL",
        "name": "directive"
      }
    },
    "directive": {
      "type": "SEQ",
      "members": [
        {
          "type": "STRING",
          "value": "@"
        },
        {
          "type": "SYMBOL",
          "name": "name"
        },
        {
          "type": "CHOICE",
          "members": [
            {
              "type": "SYMBOL",
              "name": "arguments"
            },
            {
              "type": "BLANK"
            }
          ]
        }
      ]
    },
    "directive_definition": {
      "type": "PREC_RIGHT",
      "value": 1,
      "content": {
        "type": "SEQ",
        "members": [
          {
            "type": "CHOICE",
            "members": [
              {
                "type": "SYMBOL",
                "name": "description"
              },
              {
                "type": "BLANK"
              }
            ]
          },
          {
            "type": "STRING",
            "value": "directive"
          },
          {
            "type": "STRING",
            "value": "@"
          },
          {
            "type": "SYMBOL",
            "name": "name"
          },
          {
            "type": "CHOICE",
            "members": [
              {
                "type": "SYMBOL",
                "name": "arguments_definition"
              },
              {
                "type": "BLANK"
              }
            ]
          },
          {
            "type": "CHOICE",
            "members": [
              {
                "type": "STRING",
                "value": "repeatable"
              },
              {
                "type": "BLANK"
              }
            ]
          },
          {
            "type": "STRING",
            "value": "on"
          },
          {
            "type": "SYMBOL",
            "name": "directive_locations"
          }
        ]
      }
    },
    "directive_locations": {
      "type": "CHOICE",
      "members": [
        {
          "type": "SEQ",
          "members": [
            {
              "type": "SYMBOL",
              "name": "directive_locations"
            },
            {
              "type": "STRING",
              "value": "|"
            },
            {
              "type": "SYMBOL",
              "name": "directive_location"
            }
          ]
        },
        {
          "type": "SEQ",
          "members": [
            {
              "type": "CHOICE",
              "members": [
                {
                  "type": "STRING",
                  "value": "|"
                },
                {
                  "type": "BLANK"
                }
              ]
            },
            {
              "type": "SYMBOL",
              "name": "directive_location"
            }
          ]
        }
      ]
    },
    "directive_location": {
      "type": "CHOICE",
      "members": [
        {
          "type": "SYMBOL",
          "name": "executable_directive_location"
        },
        {
          "type": "SYMBOL",
          "name": "type_system_directive_location"
        }
      ]
    },
    "executable_directive_location": {
      "type": "CHOICE",
      "members": [
        {
          "type": "STRING",
          "value": "QUERY"
        },
        {
          "type": "STRING",
          "value": "MUTATION"
        },
        {
          "type": "STRING",
          "value": "SUBSCRIPTION"
        },
        {
          "type": "STRING",
          "value": "FIELD"
        },
        {
          "type": "STRING",
          "value": "FRAGMENT_DEFINITION"
        },
        {
          "type": "STRING",
          "value": "FRAGMENT_SPREAD"
        },
        {
          "type": "STRING",
          "value": "INLINE_FRAGMENT"
        },
        {
          "type": "STRING",
          "value": "VARIABLE_DEFINITION"
        }
      ]
    },
    "type_system_directive_location": {
      "type": "CHOICE",
      "members": [
        {
          "type": "STRING",
          "value": "SCHEMA"
        },
        {
          "type": "STRING",
          "value": "SCALAR"
        },
        {
          "type": "STRING",
          "value": "OBJECT"
        },
        {
          "type": "STRING",
          "value": "FIELD_DEFINITION"
        },
        {
          "type": "STRING",
          "value": "ARGUMENT_DEFINITION"
        },
        {
          "type": "STRING",
          "value": "INTERFACE"
        },
        {
          "type": "STRING",
          "value": "UNION"
        },
        {
          "type": "STRING",
          "value": "ENUM"
        },
        {
          "type": "STRING",
          "value": "ENUM_VALUE"
        },
        {
          "type": "STRING",
          "value": "INPUT_OBJECT"
        },
        {
          "type": "STRING",
          "value": "INPUT_FIELD_DEFINITION"
        }
      ]
    },
    "type": {
      "type": "CHOICE",
      "members": [
        {
          "type": "SYMBOL",
          "name": "named_type"
        },
        {
          "type": "SYMBOL",
          "name": "list_type"
        },
        {
          "type": "SYMBOL",
          "name": "non_null_type"
        }
      ]
    },
    "named_type": {
      "type": "SYMBOL",
      "name": "name"
    },
    "list_type": {
      "type": "SEQ",
      "members": [
        {
          "type": "STRING",
          "value": "["
        },
        {
          "type": "SYMBOL",
          "name": "type"
        },
        {
          "type": "STRING",
          "value": "]"
        }
      ]
    },
    "non_null_type": {
      "type": "CHOICE",
      "members": [
        {
          "type": "SEQ",
          "members": [
            {
              "type": "SYMBOL",
              "name": "named_type"
            },
            {
              "type": "STRING",
              "value": "!"
            }
          ]
        },
        {
          "type": "SEQ",
          "members": [
            {
              "type": "SYMBOL",
              "name": "list_type"
            },
            {
              "type": "STRING",
              "value": "!"
            }
          ]
        }
      ]
    },
    "name": {
      "type": "PATTERN",
      "value": "[_A-Za-z][_0-9A-Za-z]*"
    },
    "comment": {
      "type": "TOKEN",
      "content": {
        "type": "SEQ",
        "members": [
          {
            "type": "STRING",
            "value": "#"
          },
          {
            "type": "PATTERN",
            "value": ".*"
          }
        ]
      }
    },
    "comma": {
      "type": "STRING",
      "value": ","
    },
    "description": {
      "type": "SYMBOL",
      "name": "string_value"
    }
  },
  "extras": [
    {
      "type": "PATTERN",
      "value": "[\\s\\uFEFF\\u0009\\u0020\\u000A\\u000D]"
    },
    {
      "type": "SYMBOL",
      "name": "comma"
    },
    {
      "type": "SYMBOL",
      "name": "comment"
    }
  ],
  "conflicts": [],
  "precedences": [],
  "externals": [],
  "inline": [],
  "supertypes": []
}

